.gitignore
.readthedocs.yml
.travis.yml
CHANGELOG.rst
LICENSE
MANIFEST.in
README.rst
setup.cfg
setup.py
tox.ini
docs/Makefile
docs/conf.py
docs/index.rst
docs/installation.rst
docs/_static/custom.css
docs/_static/favicon.ico
docs/_static/logo.png
docs/_static/logo_packed.png
docs/_templates/about.html
docs/api/index.rst
docs/usage/standalone.rst
docs/usage/tendril.rst
src/tendril/__init__.py
src/tendril/common/__init__.py
src/tendril/common/streams/__init__.py
src/tendril/common/streams/exceptions.py
src/tendril/tx/__init__.py
src/tendril/tx/engines/__init__.py
src/tendril/tx/engines/stream_reactor/__init__.py
src/tendril/tx/engines/stream_reactor/channel.py
src/tendril/tx/engines/stream_reactor/core.py
src/tendril/tx/engines/stream_reactor/metrics.py
src/tendril/tx/engines/stream_reactor/processors/__init__.py
src/tendril/tx/engines/stream_reactor/processors/base.py
src/tendril/tx/engines/stream_reactor/processors/rlc.py
src/tendril_tx_streamreactor.egg-info/PKG-INFO
src/tendril_tx_streamreactor.egg-info/SOURCES.txt
src/tendril_tx_streamreactor.egg-info/dependency_links.txt
src/tendril_tx_streamreactor.egg-info/requires.txt
src/tendril_tx_streamreactor.egg-info/top_level.txt
tests/__init__.py
tests/coveralls.py