Metadata-Version: 2.1
Name: tendril-tx-streamreactor
Version: 0.1.0
Summary: Primitives and Utilities for Twisted Stream Reactors for Tendril
Home-page: https://github.com/tendril-framework/tendril-tx-streamreactor
Author: Chintalagiri Shashank
Author-email: shashank@chintal.in
Project-URL: Documentation, https://tendril-tx-streamreactor.readthedocs.io/en/latest
Project-URL: Bug Tracker, https://github.com/tendril-framework/tendril-tx-streamreactor/issues
Project-URL: Source Repository, https://github.com/tendril-framework/tendril-tx-streamreactor
Keywords: tendril
Platform: any
Classifier: Development Status :: 4 - Beta
Classifier: License :: OSI Approved :: GNU Affero General Public License v3 or later (AGPLv3+)
Classifier: Natural Language :: English
Classifier: Operating System :: OS Independent
Classifier: Programming Language :: Python
Classifier: Programming Language :: Python :: 2.7
Classifier: Programming Language :: Python :: 3
Classifier: Programming Language :: Python :: 3.5
Classifier: Programming Language :: Python :: 3.6
Classifier: Programming Language :: Python :: 3.7
Classifier: Programming Language :: Python :: Implementation :: CPython
Classifier: Programming Language :: Python :: Implementation :: PyPy
Requires-Python: >=2.7, !=3.0.*, !=3.1.*, !=3.2.*, !=3.3.*
Provides-Extra: docs
Provides-Extra: tests
Provides-Extra: build
Provides-Extra: publish
Provides-Extra: dev
License-File: LICENSE
